Metadata-Version: 2.1
Name: odoo12-addon-shopinvader-backend-image-proxy
Version: 12.0.1.1.0
Summary: Add possibility to replace the image URL by the proxy url set on the SE backend
Home-page: http://www.akretion.com
Author: Akretion,ACSONE SA/NV
License: AGPL-3
Platform: UNKNOWN
Classifier: Programming Language :: Python
Classifier: Framework :: Odoo
Classifier: License :: OSI Approved :: GNU Affero General Public License v3
Requires-Python: >=3.5
Requires-Dist: odoo12-addon-shopinvader-image
Requires-Dist: odoo (<12.1dev,>=12.0a)
